CHANGELOG.rst
LICENSE
MANIFEST.in
README.rst
setup.cfg
setup.py
crossword/__init__.py
crossword/compat.py
crossword/core.py
crossword/exceptions.py
crossword/format_ipuz.py
crossword/format_puz.py
crossword.egg-info/PKG-INFO
crossword.egg-info/SOURCES.txt
crossword.egg-info/dependency_links.txt
crossword.egg-info/top_level.txt