Metadata-Version: 1.1
Name: crossword
Version: 0.1.2
Summary: Python library for handling crossword puzzles
Home-page: https://github.com/svisser/crossword
Author: Simeon Visser
Author-email: simeonvisser@gmail.com
License: MIT
Keywords: crossword puzzle ipuz puz
Platform: UNKNOWN
Classifier: Development Status :: 4 - Beta
Classifier: Intended Audience :: Developers
Classifier: License :: OSI Approved :: MIT License
Classifier: Operating System :: OS Independent
Classifier: Programming Language :: Python :: 2
Classifier: Programming Language :: Python :: 2.7
Classifier: Programming Language :: Python :: 3
Classifier: Programming Language :: Python :: 3.2
Classifier: Programming Language :: Python :: 3.3
Classifier: Programming Language :: Python :: 3.4
Classifier: Topic :: Games/Entertainment :: Puzzle Games
